sl_client.py
sl_client-1.3.dist-info/METADATA
sl_client-1.3.dist-info/RECORD
sl_client-1.3.dist-info/WHEEL
sl_client-1.3.dist-info/top_level.txt
