Metadata-Version: 2.1
Name: sl-client
Version: 1.3
Summary: A Python tool that connects to the Studyportals ServiceLayer using Studyportals reflector and retrieves data.
Home-page: https://github.com/studyportals/ServiceLayerClient-python
Author: Ugne Laima Ciziute
Author-email: devops@studyportals.com
License: BSD 3-Clause
Platform: UNKNOWN
Requires-Dist: requests
